cn_engine_linux/__init__.py
cn_engine_linux/cnsearch.py
cn_engine_linux/cnserver.py
cn_engine_linux/cnview.py
CnEngineLinux-0.1.5.dist-info/METADATA
CnEngineLinux-0.1.5.dist-info/WHEEL
CnEngineLinux-0.1.5.dist-info/entry_points.txt
CnEngineLinux-0.1.5.dist-info/top_level.txt
CnEngineLinux-0.1.5.dist-info/RECORD
