Metadata-Version: 2.1
Name: CnEngineLinux
Version: 0.1.5
Summary: CnEngine v0.1.5 is a lightweight console-based communication protocol with CN (basic), CNSS (secure SSL), and CNF (file delivery) protocols. It includes a custom language for creating structured console pages.
Home-page: https://rasmnout.github.io
Author: Rasmnout
Author-email: rasmnout@gmail.com
License: MIT
Classifier: Programming Language :: Python :: 3
Classifier: License :: OSI Approved :: MIT License
Classifier: Operating System :: OS Independent
Requires-Python: >=3.6
Requires-Dist: pyopenssl
